trytls/__init__.py
trytls/gencert.py
trytls/results.py
trytls/runner.py
trytls/testenv.py
trytls/utils.py
trytls/bundles/__init__.py
trytls/bundles/https.py
trytls/formatters/__init__.py
trytls/formatters/_utils.py
trytls/formatters/default.py
trytls/formatters/json.py
trytls-0.3.7.dist-info/DESCRIPTION.rst
trytls-0.3.7.dist-info/METADATA
trytls-0.3.7.dist-info/RECORD
trytls-0.3.7.dist-info/WHEEL
trytls-0.3.7.dist-info/entry_points.txt
trytls-0.3.7.dist-info/metadata.json
trytls-0.3.7.dist-info/top_level.txt
