Metadata-Version: 2.0
Name: trytls
Version: 0.3.7
Summary: Does your library check TLS certificates properly?
Home-page: https://github.com/ouspg/trytls
Author: UNKNOWN
Author-email: UNKNOWN
License: MIT
Platform: UNKNOWN
Requires-Dist: colorama
Requires-Dist: oscrypto
Requires-Dist: certbuilder
